README.md
setup.cfg
setup.py
BLECryptracer_BLEMAP/BLECryptracer.py
BLECryptracer_BLEMAP/__init__.py
BLECryptracer_BLEMAP.egg-info/PKG-INFO
BLECryptracer_BLEMAP.egg-info/SOURCES.txt
BLECryptracer_BLEMAP.egg-info/dependency_links.txt
BLECryptracer_BLEMAP.egg-info/requires.txt
BLECryptracer_BLEMAP.egg-info/top_level.txt
BLECryptracer_BLEMAP/common/__init__.py
BLECryptracer_BLEMAP/common/constants.py
BLECryptracer_BLEMAP/common/hash.py
BLECryptracer_BLEMAP/getvalue/__init__.py
BLECryptracer_BLEMAP/getvalue/worker_getvalue.py
BLECryptracer_BLEMAP/setvalue/__init__.py
BLECryptracer_BLEMAP/setvalue/worker_setvalue.py
BLECryptracer_BLEMAP/uuids/__init__.py
BLECryptracer_BLEMAP/uuids/main_uuid.py
BLECryptracer_BLEMAP/uuids/worker_uuid.py
BLECryptracer_BLEMAP/uuids/android-8/__init__.py