Metadata-Version: 2.1
Name: BLECryptracer-BLEMAP
Version: 0.0.7
Summary: A small example package
Home-page: https://github.com/guizos/BLECryptracer_BLEMAP
Author: guizos
Author-email: guizos@mail.com
License: UNKNOWN
Platform: UNKNOWN
Classifier: Programming Language :: Python :: 3
Classifier: License :: OSI Approved :: MIT License
Classifier: Operating System :: OS Independent
Requires-Python: >=3.6
